{
	"name": "df_gold_dim_direccion",
	"properties": {
		"folder": {
			"name": "GOLD"
		},
		"type": "MappingDataFlow",
		"typeProperties": {
			"sources": [
				{
					"dataset": {
						"referenceName": "ds_sql_silver_llamadas_entel",
						"type": "DatasetReference"
					},
					"name": "source1"
				}
			],
			"sinks": [
				{
					"dataset": {
						"referenceName": "ds_dim_direccion",
						"type": "DatasetReference"
					},
					"name": "sink1"
				}
			],
			"transformations": [],
			"scriptLines": [
				"source(output(",
				"          direccion as string",
				"     ),",
				"     allowSchemaDrift: true,",
				"     validateSchema: false,",
				"     isolationLevel: 'READ_UNCOMMITTED',",
				"     query: 'SELECT DISTINCT\\n  CAST(REGISTRO AS VARCHAR(15)) AS direccion\\nFROM SILVER.LLAMADA\\nWHERE REGISTRO IS NOT NULL\\n',",
				"     format: 'query') ~> source1",
				"source1 sink(allowSchemaDrift: true,",
				"     validateSchema: false,",
				"     input(",
				"          id_direccion as integer,",
				"          direccion as string",
				"     ),",
				"     deletable:false,",
				"     insertable:true,",
				"     updateable:false,",
				"     upsertable:false,",
				"     format: 'table',",
				"     skipDuplicateMapInputs: true,",
				"     skipDuplicateMapOutputs: true,",
				"     errorHandlingOption: 'stopOnFirstError',",
				"     mapColumn(",
				"          direccion",
				"     )) ~> sink1"
			]
		}
	}
}