{
	"name": "ds_sql_silver_datos_entel",
	"properties": {
		"linkedServiceName": {
			"referenceName": "ls_sql_dw_entel",
			"type": "LinkedServiceReference"
		},
		"folder": {
			"name": "Silver"
		},
		"annotations": [],
		"type": "AzureSqlTable",
		"schema": [
			{
				"name": "FECHA_INICIO",
				"type": "datetime2",
				"scale": 7
			},
			{
				"name": "FECHA_FIN",
				"type": "datetime2",
				"scale": 7
			},
			{
				"name": "NUMERO",
				"type": "varchar"
			},
			{
				"name": "IMEI",
				"type": "varchar"
			},
			{
				"name": "RBS_UTILIZADA",
				"type": "varchar"
			},
			{
				"name": "CELDA",
				"type": "int",
				"precision": 10
			},
			{
				"name": "LATITUD_LONGITUD",
				"type": "varchar"
			},
			{
				"name": "SUBIDOS",
				"type": "bigint",
				"precision": 19
			},
			{
				"name": "DESCARGADOS",
				"type": "bigint",
				"precision": 19
			},
			{
				"name": "TOTAL",
				"type": "bigint",
				"precision": 19
			}
		],
		"typeProperties": {
			"schema": "SILVER",
			"table": "DATOS"
		}
	}
}